membank/__init__.py
membank/connplug.py
membank/datamapper.py
membank/datamethods.py
membank/errors.py
membank/interface.py
membank/py.typed
membank-0.5.6.dist-info/METADATA
membank-0.5.6.dist-info/WHEEL
membank-0.5.6.dist-info/top_level.txt
membank-0.5.6.dist-info/RECORD
