Metadata-Version: 2.4
Name: membank
Version: 0.5.6
Summary: A library to handle persistent memory
Author-email: Juris Kaminskis <juris@kolumbs.net>
Project-URL: Repository, https://github.com/Kolumbs/membank
Classifier: Development Status :: 1 - Planning
Classifier: Intended Audience :: Developers
Classifier: Programming Language :: Python :: 3
Classifier: License :: OSI Approved :: BSD License
Classifier: Operating System :: OS Independent
Classifier: Topic :: Database
Requires-Python: >=3.10
Requires-Dist: alembic
Requires-Dist: asyncpg
Requires-Dist: sqlalchemy
